{
  "_id": "IUWkURAO95yECnyh",
  "data": {
    "description": {
      "@en": "The secrets of Elder Futhark have been passed down by generations. However, Rune Jarls have mastered a simpler, battle-ready form called Younger Futhark. These runes possess even more power than their forbearers."
    },
    "notes": "",
    "rules": {
      "effect": {
        "@en": "You reduce the binding time to one hour for Apprentice Runes, two hours for Journeyman Runes and three hours for Master Runes. Furthermore, the items you inscribe can bear up to 6 Apprentice, 4 Journeyman or 2 Master Runes. Finally, any object you inscribe a Rune upon (including buildings, vehicles or objects larger than a man is tall) takes upon the benefits of the Rune."
      }
    }
  },
  "effects": [],
  "flags": {},
  "folder": null,
  "img": "systems/zweihander/assets/icons/vitruvian-man.svg",
  "name": "Younger Futhark",
  "permission": {
    "JyjuBRFhP4y9QWxg": 3,
    "default": 0
  },
  "sort": 0,
  "type": "trait"
}
