{
  "_id": "3Tm5w0gKdMocZL3l",
  "effects": [],
  "img": "systems/zweihander/assets/icons/spiked-halo.svg",
  "name": "Sour Stomach",
  "type": "drawback",
  "_stats": {
    "coreVersion": "13.342",
    "systemId": null,
    "systemVersion": null,
    "createdTime": null,
    "modifiedTime": 1733923835859,
    "lastModifiedBy": "rivg6xcMxdlVDM8y",
    "compendiumSource": null,
    "duplicateSource": null,
    "exportSource": null
  },
  "system": {
    "description": {
      "@en": "You have pains in your stomach that make it difficult to keep down ‘rich’ food. This also means other kinds of substances can have a poor effect on your health, and keep you confined to the water closet."
    },
    "notes": "",
    "rules": {
      "effect": {
        "@en": "After taking a dose of Laudanum, a Delirient or consuming a substance the GM sees as being hard on your stomach, you cannot recover to Unhindered on the Peril Condition Track (only to Imperiled) for the next 24-hours."
      }
    }
  },
  "folder": null,
  "sort": 1100000,
  "ownership": {
    "default": 0
  },
  "flags": {},
  "_key": "!items!3Tm5w0gKdMocZL3l"
}
