{
  "_id": "XvJUgS8eoQYAZdf2",
  "effects": [],
  "img": "systems/zweihander/assets/icons/transfuse.svg",
  "name": "Sanguine Restoration",
  "type": "spell",
  "_stats": {
    "coreVersion": "13.342",
    "systemId": "zweihander",
    "systemVersion": "5.4.1",
    "createdTime": null,
    "modifiedTime": 1745410666700,
    "lastModifiedBy": "rivg6xcMxdlVDM8y",
    "compendiumSource": null,
    "duplicateSource": null,
    "exportSource": null
  },
  "system": {
    "description": {
      "@en": "The blood of another invigorates."
    },
    "notes": "",
    "rules": {
      "effect": {
        "@en": "After successfully casting this spell, you move one step up the Damage Condition Track positively. However, you suffer 3 Corruption as a result."
      },
      "criticalSuccess": {
        "@en": "As above, but you don’t suffer any Corruption whatsoever."
      },
      "criticalFailure": {
        "@en": "As you drink deep from the vial, the blood tastes of ash. It cannot sate your own predilection for fresh blood. If you do not drink the blood from one of your own Ancestry within 24 hours, you move one step down the Damage Condition Track negatively (but don’t suffer an Injury due to it)."
      },
      "reagents": {
        "@en": "A pint of blood from one of your own Ancestry, imbibed (expended)"
      }
    },
    "tradition": "Arcane (Necromancy)",
    "principle": "Petty",
    "distance": "Yourself",
    "duration": {
      "value": "instantaneous",
      "label": "Instantaneous",
      "formula": {
        "override": false
      },
      "base": "[WB]",
      "bonus": 0,
      "unit": "Instantaneous"
    },
    "castingTime": "1 min",
    "castingCost": 0
  },
  "folder": null,
  "sort": 0,
  "ownership": {
    "default": 0
  },
  "flags": {},
  "_key": "!items!XvJUgS8eoQYAZdf2"
}
