{
  "_id": "GVpa5lVWCJJbor4m",
  "effects": [],
  "img": "systems/zweihander/assets/icons/middle-arrow.svg",
  "name": "Take ‘em Down",
  "type": "talent",
  "_stats": {
    "coreVersion": "13.342",
    "systemId": null,
    "systemVersion": null,
    "createdTime": null,
    "modifiedTime": null,
    "lastModifiedBy": null,
    "compendiumSource": null,
    "duplicateSource": null,
    "exportSource": null
  },
  "system": {
    "description": {
      "@en": "A perfect throw can bring down your quarry as they run away. With a carefully-placed shot, you can disarm or knock down any foe."
    },
    "notes": "",
    "rules": {
      "effect": {
        "@en": "At Distance, you can substitute either your Simple Ranged or Martial Ranged Skills when you attempt to use Disarm, Stunning Blow or Takedown. Note that you do not inflict Damage when you attempt such maneuvers. You must be armed with a loaded ranged weapon in order to Take ‘Em Down."
      }
    },
    "purchased": false
  },
  "folder": null,
  "sort": 0,
  "ownership": {
    "default": 0
  },
  "flags": {},
  "_key": "!items!GVpa5lVWCJJbor4m"
}
