{
  "_id": "PPjAbMws34gLYLn4",
  "data": {
    "description": {
      "@en": "<p>I fear that my enemies have underestimated my power while in the saddle.</p>"
    },
    "notes": "<p>Every Profession possesses a unique knack, an ability that no other Profession has access to. The Trait immediately follows the Profession&rsquo;s description.</p>",
    "rules": {
      "effect": {
        "@en": "<p>Every time you inflict Damage on horseback using Actions In Combat, temporarily increase your Total Damage by +1 cumulatively, lasting until you are Slain! or combat ends.</p>"
      }
    }
  },
  "effects": [],
  "flags": {
    "core": {
      "sourceId": "Compendium.zweihander.traits.50e9efsnnz7kvvFM"
    },
    "scene-packer": {
      "hash": "48f3eae299f243abed4dd8b314fa4aee98ce5534",
      "sourceId": "Item.PPjAbMws34gLYLn4"
    }
  },
  "folder": null,
  "img": "systems/zweihander/assets/icons/vitruvian-man.svg",
  "name": "Devil in the Saddle",
  "permission": {
    "VOagSWOxwT3osUDT": 3,
    "default": 0
  },
  "sort": 0,
  "type": "trait"
}
