{
  "_id": "uxhl3bPhHpwt54mg",
  "data": {
    "description": {
      "@en": "<p><em>I cut, sew and measure&mdash;all the while keeping an eye on who&rsquo;s </em><em>coming and going.</em></p>"
    },
    "notes": "<p>Every Profession possesses a unique knack, an ability that no other Profession has access to. The Trait immediately follows the Profession&rsquo;s description.</p>",
    "rules": {
      "effect": {
        "@en": "<p>When you fail a Charm or Eavesdrop Test, you may re-roll to generate a better result, but must accept the outcome. In addition, you always succeed at Skill Tests to accurately estimate Distances.</p>"
      }
    }
  },
  "effects": [],
  "flags": {
    "core": {
      "sourceId": "Compendium.zweihander.traits.50e9efsnnz7kvvFM"
    },
    "scene-packer": {
      "hash": "74f74737d04001bf116812e4113be37970ff2a2e",
      "sourceId": "Item.uxhl3bPhHpwt54mg"
    }
  },
  "folder": null,
  "img": "systems/zweihander/assets/icons/vitruvian-man.svg",
  "name": "Respect the Drip",
  "permission": {
    "VOagSWOxwT3osUDT": 3,
    "default": 0
  },
  "sort": 0,
  "type": "trait"
}
