{
  "_id": "TyucqA7liqzV0tCD",
  "data": {
    "description": {
      "@en": ""
    },
    "notes": "",
    "rules": {
      "effect": {
        "@en": "When foes Parry this creature’s melee attack, it can make an Opportunity Attack at this same foe."
      }
    }
  },
  "effects": [],
  "flags": {},
  "folder": null,
  "img": "systems/zweihander/assets/icons/vitruvian-man.svg",
  "name": "Chomp",
  "permission": {
    "JyjuBRFhP4y9QWxg": 3,
    "default": 0
  },
  "sort": 0,
  "type": "trait"
}
