{
  "_id": "JRfF8yASBUdxOB9C",
  "_stats": {
    "coreVersion": "10.290",
    "createdTime": null,
    "lastModifiedBy": "Utysx5mMgmUGpIMt",
    "modifiedTime": 1670078243579,
    "systemId": "zweihander",
    "systemVersion": "5.0.4"
  },
  "effects": [],
  "flags": {},
  "folder": null,
  "img": "systems/zweihander/assets/icons/bullet-impacts.svg",
  "name": "Point Blank",
  "ownership": {
    "JyjuBRFhP4y9QWxg": 3,
    "default": 0
  },
  "sort": 0,
  "system": {
    "description": {
      "@en": ""
    },
    "notes": "",
    "rules": {
      "effect": {
        "@en": "When these creatures make an Attack Action with a weapon possessing the Gunpowder Quality within Short Distance, they add an additional 1D6 Fury Die to Damage."
      }
    }
  },
  "type": "trait"
}
