{
  "_id": "QaoEKQx3WgkIUHQe",
  "effects": [],
  "img": "systems/zweihander/assets/icons/scythe.svg",
  "name": "Weeping Scythe",
  "system": {
    "description": {
      "@en": ""
    },
    "notes": "",
    "rules": {
      "effect": {
        "@en": "When these creatures are encountered, they carry a scythe infused with the blood of mortals. When they deal Damage, the foe also begins to Bleed. This can only be used in the hands of these creatures, being otherwise useless relics to others. If picked up by PCs whose Order Ranks are higher than their Chaos Ranks, they are instantly disintegrated into ash, Slain!."
      }
    }
  },
  "type": "trait"
}
